dora_base/__init__.py
dora_base/disk.py
dora_base/logger_setup.py
dora_base/runtime_info.py
dora_base-0.1.0.dist-info/METADATA
dora_base-0.1.0.dist-info/WHEEL
dora_base-0.1.0.dist-info/RECORD
