Metadata-Version: 2.1
Name: dora-base
Version: 0.1.0
Summary: Add your description here
Author-email: lijianan <lijianan@tezign.com>
Requires-Python: >=3.8
Requires-Dist: loguru>=0.7.2
Requires-Dist: pyyaml>=6.0.1
Requires-Dist: requests>=2.31.0
